usbimager/__init__.py
usbimager/__main__.py
usbimager/shared_objects.py
usbimager/threads.py
usbimager/ui_application.py
usbimager/ui_mainwindow.py
usbimager/ui_targetwidget.py
usbimager/modules/__init__.py
usbimager/modules/filesize.py
usbimager/modules/msgbox.py
usbimager/modules/timer.py
usbimager/modules/udisks2.py
usbimager/resources/__init__.py
usbimager/resources/usb-imager.ico
usb_imager-2.2.2.data/data/share/applications/usb-imager.desktop
usb_imager-2.2.2.data/data/share/icons/hicolor/128x128/apps/usb-imager.png
usb_imager-2.2.2.data/data/share/icons/hicolor/16x16/apps/usb-imager.png
usb_imager-2.2.2.data/data/share/icons/hicolor/24x24/apps/usb-imager.png
usb_imager-2.2.2.data/data/share/icons/hicolor/32x32/apps/usb-imager.png
usb_imager-2.2.2.data/data/share/icons/hicolor/48x48/apps/usb-imager.png
usb_imager-2.2.2.data/data/share/icons/hicolor/64x64/apps/usb-imager.png
usb_imager-2.2.2.data/data/share/icons/hicolor/72x72/apps/usb-imager.png
usb_imager-2.2.2.dist-info/entry_points.txt
usb_imager-2.2.2.dist-info/LICENSE.rst
usb_imager-2.2.2.dist-info/WHEEL
usb_imager-2.2.2.dist-info/METADATA
usb_imager-2.2.2.dist-info/RECORD
