Metadata-Version: 2.1
Name: USB-Imager
Version: 2.2.2
Summary: GUI-Application to write bootable disk images to USB keys
Keywords: usb,image,img,iso,write,writer,dd,flash,boot
Author-email: Skynet-Devel <skynet.devel@secu-design.com>
Requires-Python: >=3.9
Classifier: Development Status :: 5 - Production/Stable
Classifier: License :: OSI Approved :: GNU General Public License v3 or later (GPLv3+)
Classifier: Intended Audience :: End Users/Desktop
Classifier: Topic :: System
Classifier: Topic :: Utilities
Classifier: Operating System :: POSIX :: Linux
Classifier: Programming Language :: Python :: 3 :: Only
Classifier: Programming Language :: Python :: 3.9
Classifier: Natural Language :: English
Requires-Dist: PySide2
Requires-Dist: PyGObject
Project-URL: GitLab, https://gitlab.com/secu-design/usb-imager
Project-URL: PyPI, https://pypi.org/project/usb-imager
